easy_yapi/__init__.py
easy_yapi/base_api.py
easy_yapi/cli.py
easy_yapi/easy_yapi.py
easy_yapi/group.py
easy_yapi/project.py
easy_yapi/user.py
easy_yapi-0.1.2.dist-info/AUTHORS.rst
easy_yapi-0.1.2.dist-info/LICENSE
easy_yapi-0.1.2.dist-info/METADATA
easy_yapi-0.1.2.dist-info/WHEEL
easy_yapi-0.1.2.dist-info/entry_points.txt
easy_yapi-0.1.2.dist-info/top_level.txt
easy_yapi-0.1.2.dist-info/RECORD
