Metadata-Version: 2.1
Name: easy-yapi
Version: 0.1.2
Summary: Yapi Python SDK
Home-page: https://github.com/nocoding126/easy_yapi
Author: 派大星
Author-email: nocoding@126.com
License: MIT license
Keywords: easy_yapi,yapi
Classifier: Development Status :: 2 - Pre-Alpha
Classifier: Intended Audience :: Developers
Classifier: License :: OSI Approved :: MIT License
Classifier: Natural Language :: English
Classifier: Programming Language :: Python :: 3
Classifier: Programming Language :: Python :: 3.9
Classifier: Programming Language :: Python :: 3.10
Classifier: Programming Language :: Python :: 3.11
Requires-Python: >=3.6
License-File: LICENSE
License-File: AUTHORS.rst
Requires-Dist: Click (>=7.0)
Requires-Dist: requests
